comfy_mcp_server/__init__.py
comfy_mcp_server-0.1.11.dist-info/METADATA
comfy_mcp_server-0.1.11.dist-info/WHEEL
comfy_mcp_server-0.1.11.dist-info/entry_points.txt
comfy_mcp_server-0.1.11.dist-info/licenses/LICENSE
comfy_mcp_server-0.1.11.dist-info/RECORD
