Metadata-Version: 2.4
Name: comfy-mcp-server
Version: 0.1.11
Summary: MCP Server for ComfyUI text to image Workflow
Project-URL: Homepage, https://github.com/lalanikarim/comfy-mcp-server/
Project-URL: Repository, https://github.com/lalanikarim/comfy-mcp-server/
Author-email: Karim Lalani <jimmy00784@gmail.com>
Maintainer-email: Karim Lalani <jimmy00784@gmail.com>
License-Expression: MIT
License-File: LICENSE
Requires-Python: >=3.10
Requires-Dist: langchain-ollama>=0.2.3
Requires-Dist: langchain>=0.3.19
Requires-Dist: mcp[cli]>=1.2.1
